brs/__init__.py
brs/bits.py
brs/brs.py
brs/color.py
brs/orientation.py
brs/reader.py
brs/user.py
brs/utils.py
brs/writer.py
brs_py-0.5.2.dist-info/LICENSE
brs_py-0.5.2.dist-info/METADATA
brs_py-0.5.2.dist-info/WHEEL
brs_py-0.5.2.dist-info/top_level.txt
brs_py-0.5.2.dist-info/RECORD
