Metadata-Version: 2.1
Name: brs-py
Version: 0.5.2
Summary: Brickadia savefile reader/writer
Home-page: https://www.github.com/Kmschr/brs-py
Author: Kevin Schroeder
Author-email: Kmschr@gmail.com
License: UNKNOWN
Platform: UNKNOWN
Classifier: Programming Language :: Python :: 3
Classifier: License :: OSI Approved :: MIT License
Classifier: Operating System :: OS Independent
Requires-Python: >=3.6
